mosaik_scenario_tools/scenario_tools/__init__.py
mosaik_scenario_tools/scenario_tools/compressed_data_flow/__init__.py
mosaik_scenario_tools/scenario_tools/compressed_data_flow/create_deflate_source_model_module.py
mosaik_scenario_tools/scenario_tools/compressed_data_flow/create_inflate_sink_model_module.py
mosaik_scenario_tools/scenario_tools/compressed_data_flow/deflate_inflate_scenario_module.py
mosaik_scenario_tools/scenario_tools/compressed_data_flow/deflate_module.py
mosaik_scenario_tools/scenario_tools/compressed_data_flow/deflate_simulator.py
mosaik_scenario_tools/scenario_tools/compressed_data_flow/deflate_simulator_meta.py
mosaik_scenario_tools/scenario_tools/compressed_data_flow/deflate_source_model.py
mosaik_scenario_tools/scenario_tools/compressed_data_flow/inflate_module.py
mosaik_scenario_tools/scenario_tools/compressed_data_flow/inflate_simulator.py
mosaik_scenario_tools/scenario_tools/compressed_data_flow/inflate_simulator_meta.py
mosaik_scenario_tools/scenario_tools/compressed_data_flow/inflate_sink_model.py
mosaik_scenario_tools/scenario_tools/connect/__init__.py
mosaik_scenario_tools/scenario_tools/connect/connect_many_to_one_module.py
mosaik_scenario_tools/scenario_tools/connect/connect_one_to_many_module.py
mosaik_scenario_tools/scenario_tools/connect/connect_one_to_one_module.py
mosaik_scenario_tools/scenario_tools/create/create_model_module.py
mosaik_scenario_tools/scenario_tools/create/create_world_module.py
mosaik_scenario_tools/scenario_tools/model/__init__.py
mosaik_scenario_tools/scenario_tools/model/get_first_source_key_module.py
mosaik_scenario_tools/scenario_tools/port/find_free_port_module.py
mosaik_scenario_tools/scenario_tools/simulator/__init__.py
mosaik_scenario_tools/scenario_tools/simulator/buffer_inputs/__init__.py
mosaik_scenario_tools/scenario_tools/simulator/buffer_inputs/buffer_inputs_module.py
mosaik_scenario_tools/scenario_tools/simulator/buffer_inputs/input_buffering_meta.py
mosaik.Scenario_Tools-0.1.0rc20221002000505.dist-info/AUTHORS.txt
mosaik.Scenario_Tools-0.1.0rc20221002000505.dist-info/LICENSE.txt
mosaik.Scenario_Tools-0.1.0rc20221002000505.dist-info/METADATA
mosaik.Scenario_Tools-0.1.0rc20221002000505.dist-info/WHEEL
mosaik.Scenario_Tools-0.1.0rc20221002000505.dist-info/top_level.txt
mosaik.Scenario_Tools-0.1.0rc20221002000505.dist-info/RECORD
